md2svg_mcp/__init__.py
md2svg_mcp/md2svg_mcp.py
md2svg_mcp-0.1.8.dist-info/METADATA
md2svg_mcp-0.1.8.dist-info/WHEEL
md2svg_mcp-0.1.8.dist-info/entry_points.txt
md2svg_mcp-0.1.8.dist-info/RECORD
