Metadata-Version: 2.4
Name: md2svg-mcp
Version: 0.1.8
Summary: A MCP server that converts Markdown text to SVG images.
Project-URL: Homepage, https://github.com/yossi-lee/md2svg-mcp
Project-URL: Issues, https://github.com/yossi-lee/md2svg-mcp/issues
Author: Yossi-lee
Keywords: markdown,mcp,svg
Requires-Python: >=3.11
Requires-Dist: fastmcp
